bsn_sdk_py/__init__.py
bsn_sdk_py/setup.py
bsn_sdk_py/client/__init__.py
bsn_sdk_py/client/bsn_enum.py
bsn_sdk_py/client/config.py
bsn_sdk_py/client/exceptions.py
bsn_sdk_py/client/fabric_client.py
bsn_sdk_py/client/entity/__init__.py
bsn_sdk_py/client/entity/bsn_base.py
bsn_sdk_py/client/entity/enroll_user.py
bsn_sdk_py/client/entity/event_query.py
bsn_sdk_py/client/entity/event_register.py
bsn_sdk_py/client/entity/event_remove.py
bsn_sdk_py/client/entity/get_block_info.py
bsn_sdk_py/client/entity/get_ledger_info.py
bsn_sdk_py/client/entity/get_transaction.py
bsn_sdk_py/client/entity/no_trust_trans.py
bsn_sdk_py/client/entity/register_user.py
bsn_sdk_py/client/entity/req_chain_code.py
bsn_sdk_py/common/__init__.py
bsn_sdk_py/common/aes.py
bsn_sdk_py/common/api_requestor.py
bsn_sdk_py/common/bsn_encrypt.py
bsn_sdk_py/common/myecdsa256.py
bsn_sdk_py/common/sm.py
bsn_sdk_py/test/__init__.py
bsn_sdk_py/test/getAppInfo.py
bsn_sdk_py/test/register_user.py
bsn_sdk_py/trans/__init__.py
bsn_sdk_py/trans/not_trust_trans_request.py
bsn_sdk_py/trans/protobuf_test.py
bsn_sdk_py/trans/transaction_header.py
bsn_sdk_py/trans/protobuf_entity/__init__.py
bsn_sdk_py/trans/protobuf_entity/common/__init__.py
bsn_sdk_py/trans/protobuf_entity/common/collection_pb2.py
bsn_sdk_py/trans/protobuf_entity/common/common_pb2.py
bsn_sdk_py/trans/protobuf_entity/common/configtx_pb2.py
bsn_sdk_py/trans/protobuf_entity/common/configuration_pb2.py
bsn_sdk_py/trans/protobuf_entity/common/ledger_pb2.py
bsn_sdk_py/trans/protobuf_entity/common/policies_pb2.py
bsn_sdk_py/trans/protobuf_entity/msp/__init__.py
bsn_sdk_py/trans/protobuf_entity/msp/identities_pb2.py
bsn_sdk_py/trans/protobuf_entity/msp/msp_config_pb2.py
bsn_sdk_py/trans/protobuf_entity/msp/msp_principal_pb2.py
bsn_sdk_py/trans/protobuf_entity/peer/__init__.py
bsn_sdk_py/trans/protobuf_entity/peer/chaincode_pb2.py
bsn_sdk_py/trans/protobuf_entity/peer/proposal_pb2.py
bsn_sdk_py/trans/protobuf_entity/peer/proposal_response_pb2.py
bsn_sdk_py-1.0.6.dist-info/LICENSE
bsn_sdk_py-1.0.6.dist-info/METADATA
bsn_sdk_py-1.0.6.dist-info/WHEEL
bsn_sdk_py-1.0.6.dist-info/top_level.txt
bsn_sdk_py-1.0.6.dist-info/RECORD
