Metadata-Version: 2.1
Name: bsn-sdk-py
Version: 1.0.6
Summary: this is the bsn Call the gateway sdk
Home-page: https://github.com/BSNDA/PCNGateway-PY-SDK
Author: helailiang
Author-email: helailiang@reddatetech.com
License: MIT Licence
Keywords: bsn,fabric,bsnbase,bsn_sdk_py,bsn_sdk_python
Platform: any
Classifier: Programming Language :: Python :: 3
Classifier: License :: OSI Approved :: MIT License
Classifier: Operating System :: OS Independent
Requires-Python: >=3.6
Requires-Dist: hkdf (==0.0.3)
Requires-Dist: cryptography (==2.7)
Requires-Dist: fabric-sdk-py (==0.8.1)
